Metadata-Version: 2.1
Name: dprop
Version: 0.42
Summary: Everything is connected, maan!
Home-page: UNKNOWN
Author: Kosio Karchev
Author-email: kosiokarchev@gmail.com
License: MIT
Project-URL: GitHub, https://github.com/kosiokarchev/dprop
Platform: UNKNOWN
Classifier: License :: OSI Approved :: MIT License
Classifier: Programming Language :: Python :: 3
Classifier: Programming Language :: Python :: 3.8
Classifier: Programming Language :: Python :: 3.9
Classifier: Programming Language :: Python :: 3.10
Requires-Python: >=3.8
Provides-Extra: testing
